azure/cognitiveservices/language/textanalytics/__init__.py
azure/cognitiveservices/language/textanalytics/py.typed
azure/cognitiveservices/language/textanalytics/text_analytics_client.py
azure/cognitiveservices/language/textanalytics/version.py
azure/cognitiveservices/language/textanalytics/models/__init__.py
azure/cognitiveservices/language/textanalytics/models/detected_language.py
azure/cognitiveservices/language/textanalytics/models/detected_language_py3.py
azure/cognitiveservices/language/textanalytics/models/document_statistics.py
azure/cognitiveservices/language/textanalytics/models/document_statistics_py3.py
azure/cognitiveservices/language/textanalytics/models/entities_batch_result.py
azure/cognitiveservices/language/textanalytics/models/entities_batch_result_item.py
azure/cognitiveservices/language/textanalytics/models/entities_batch_result_item_py3.py
azure/cognitiveservices/language/textanalytics/models/entities_batch_result_py3.py
azure/cognitiveservices/language/textanalytics/models/entity_record.py
azure/cognitiveservices/language/textanalytics/models/entity_record_py3.py
azure/cognitiveservices/language/textanalytics/models/error_record.py
azure/cognitiveservices/language/textanalytics/models/error_record_py3.py
azure/cognitiveservices/language/textanalytics/models/error_response.py
azure/cognitiveservices/language/textanalytics/models/error_response_py3.py
azure/cognitiveservices/language/textanalytics/models/internal_error.py
azure/cognitiveservices/language/textanalytics/models/internal_error_py3.py
azure/cognitiveservices/language/textanalytics/models/key_phrase_batch_result.py
azure/cognitiveservices/language/textanalytics/models/key_phrase_batch_result_item.py
azure/cognitiveservices/language/textanalytics/models/key_phrase_batch_result_item_py3.py
azure/cognitiveservices/language/textanalytics/models/key_phrase_batch_result_py3.py
azure/cognitiveservices/language/textanalytics/models/language_batch_input.py
azure_cognitiveservices_language_textanalytics-0.2.2.dist-info/LICENSE
azure_cognitiveservices_language_textanalytics-0.2.2.dist-info/METADATA
azure_cognitiveservices_language_textanalytics-0.2.2.dist-info/WHEEL
azure_cognitiveservices_language_textanalytics-0.2.2.dist-info/top_level.txt
azure_cognitiveservices_language_textanalytics-0.2.2.dist-info/RECORD
